demo/__init__.py
demo/demo_ccfa.py
demo/demo_ccfa_irt.py
demo/demo_cfa.py
demo/demo_ctt.py
demo/demo_em_dina.py
demo/demo_fa.py
demo/demo_grm.py
demo/demo_ho_dina.py
demo/demo_irt2pl.py
demo/demo_mcmc_dina.py
demo/demo_mirt2pl.py
demo/demo_sem.py
demo/demo_sim_adaptive.py
demo/demo_sim_ctt.py
psy/__init__.py
psy/exceptions.py
psy/cat/__init__.py
psy/cat/tirt.py
psy/cdm/__init__.py
psy/cdm/irm.py
psy/ctt/__init__.py
psy/ctt/ctt.py
psy/fa/__init__.py
psy/fa/factors.py
psy/fa/rotations.py
psy/mirt/__init__.py
psy/mirt/grm.py
psy/mirt/irm.py
psy/sem/__init__.py
psy/sem/ccfa.py
psy/sem/cfa.py
psy/sem/sem.py
psy/settings/__init__.py
psy/settings/cat.py
psy/settings/mirt.py
psy/utils/__init__.py
psy/utils/probs.py
psy/utils/randoms.py
psy/utils/tools.py
psy-0.0.1.dist-info/DESCRIPTION.rst
psy-0.0.1.dist-info/METADATA
psy-0.0.1.dist-info/RECORD
psy-0.0.1.dist-info/WHEEL
psy-0.0.1.dist-info/metadata.json
psy-0.0.1.dist-info/top_level.txt
pypsy/__init__.py
